{
	"animations": [
		{
			"offsets": [
				-27,
				-29
			],
			"loop": false,
			"fps": 24,
			"anim": "singDOWN",
			"indices": [
				0,
				1,
				2,
				3,
				4,
				5,
				6,
				7,
				8,
				9
			],
			"name": "down"
		},
		{
			"loop": false,
			"offsets": [
				2,
				-8
			],
			"anim": "singLEFT",
			"fps": 24,
			"name": "left",
			"indices": [
				0,
				1,
				2,
				3,
				4,
				5,
				6,
				7,
				8,
				9
			]
		},
		{
			"loop": false,
			"offsets": [
				-31,
				6
			],
			"anim": "singRIGHT",
			"fps": 24,
			"name": "right",
			"indices": [
				0,
				1,
				2,
				3,
				4,
				5,
				6,
				7,
				8,
				9
			]
		},
		{
			"loop": false,
			"offsets": [
				17,
				65
			],
			"anim": "singUP",
			"fps": 24,
			"name": "up",
			"indices": [
				0,
				1,
				2,
				3,
				4,
				5,
				6,
				7,
				8,
				9
			]
		},
		{
			"loop": false,
			"offsets": [
				-5,
				0
			],
			"anim": "idle",
			"fps": 24,
			"name": "idle",
			"indices": []
		}
	],
	"no_antialiasing": false,
	"image": "characters/infiBFEMIX",
	"position": [
		110,
		240
	],
	"healthicon": "bf-sparkle",
	"flip_x": true,
	"healthbar_colors": [
		237,
		92,
		92
	],
	"camera_position": [
		-120,
		0
	],
	"sing_duration": 4,
	"scale": 0.9
}